photo_management/__init__.py
photo_management/photo_importer.py
photo_management/photo_management.py
photo_management-2024.1.dist-info/METADATA
photo_management-2024.1.dist-info/WHEEL
photo_management-2024.1.dist-info/entry_points.txt
photo_management-2024.1.dist-info/licenses/LICENSE
photo_management-2024.1.dist-info/RECORD
